swissdox/Swissdox.py
swissdox/__init__.py
swissdox/schemas/available-schemas.yaml
swissdox/schemas/schema-1.2.json
swissdox-1.1.0.dist-info/METADATA
swissdox-1.1.0.dist-info/WHEEL
swissdox-1.1.0.dist-info/top_level.txt
swissdox-1.1.0.dist-info/RECORD
